Metadata-Version: 1.0
Name: git-tidbit
Version: 0.4
Summary: Learn something new every time you commit!
Home-page: https://github.com/savala/git-tidbit
Author: Sai Avala, Ryan Sydnor, Quan Zhou
Author-email: sai.avala@utexas.edu, ryan.t.sydnor@gmail.com, quanxzhou@gmail.com
License: MIT
Keywords: git vcs fun commit til tidbit
Platform: UNKNOWN
